LICENSE
MANIFEST.in
README.md
setup.py
django_inapp_survey.egg-info/PKG-INFO
django_inapp_survey.egg-info/SOURCES.txt
django_inapp_survey.egg-info/dependency_links.txt
django_inapp_survey.egg-info/requires.txt
django_inapp_survey.egg-info/top_level.txt
inapp_survey/__init__.py
inapp_survey/admin.py
inapp_survey/apps.py
inapp_survey/models.py
inapp_survey/resources.py
inapp_survey/serializers.py
inapp_survey/tests.py
inapp_survey/urls.py
inapp_survey/views.py
inapp_survey/docs/example.md
inapp_survey/migrations/0001_initial.py
inapp_survey/migrations/0002_auto_20210912_1311.py
inapp_survey/migrations/0003_auto_20240510_0351.py
inapp_survey/migrations/0004_alter_campaign_priority.py
inapp_survey/migrations/0005_alter_campaign_expiry_date.py
inapp_survey/migrations/__init__.py
inapp_survey/static/bower_components_inapp/Typo.js/.bower.json
inapp_survey/static/bower_components_inapp/Typo.js/README.md
inapp_survey/static/bower_components_inapp/Typo.js/SECURITY.md
inapp_survey/static/bower_components_inapp/Typo.js/license.txt
inapp_survey/static/bower_components_inapp/Typo.js/manifest.json
inapp_survey/static/bower_components_inapp/Typo.js/examples/node/index.js
inapp_survey/static/bower_components_inapp/Typo.js/tests/README.md
inapp_survey/static/bower_components_inapp/Typo.js/tests/british.html
inapp_survey/static/bower_components_inapp/Typo.js/tests/british.js
inapp_survey/static/bower_components_inapp/Typo.js/tests/english.html
inapp_survey/static/bower_components_inapp/Typo.js/tests/english.js
inapp_survey/static/bower_components_inapp/Typo.js/tests/french.html
inapp_survey/static/bower_components_inapp/Typo.js/tests/french.js
inapp_survey/static/bower_components_inapp/Typo.js/tests/general.html
inapp_survey/static/bower_components_inapp/Typo.js/tests/general.js
inapp_survey/static/bower_components_inapp/Typo.js/tests/german.html
inapp_survey/static/bower_components_inapp/Typo.js/tests/german.js
inapp_survey/static/bower_components_inapp/Typo.js/tests/index.html
inapp_survey/static/bower_components_inapp/Typo.js/tests/latin.html
inapp_survey/static/bower_components_inapp/Typo.js/tests/latin.js
inapp_survey/static/bower_components_inapp/Typo.js/tests/tests.css
