Metadata-Version: 2.1
Name: django-inapp-survey
Version: 0.2.8
Summary: A simple Django app to conduct Web-based survey or do announcement.
Home-page: https://github.com/TuvaLabs/django-inapp-survey
Author: Jaimin <jpatel@tuvalabs.com>, Naveen <nganesan@tuvalabs.com>
Author-email: support@tuvalabs.com
License: Apache License 2.0
Classifier: Environment :: Web Environment
Classifier: Framework :: Django
Classifier: Framework :: Django :: 3.2
Classifier: Intended Audience :: Developers
Classifier: License :: OSI Approved :: BSD License
Classifier: Operating System :: OS Independent
Classifier: Programming Language :: Python
Classifier: Programming Language :: Python :: 3
Classifier: Programming Language :: Python :: 3.7
Classifier: Topic :: Internet :: WWW/HTTP
Classifier: Topic :: Internet :: WWW/HTTP :: Dynamic Content
License-File: LICENSE
